ingester3/Country.py
ingester3/DBWriter.py
ingester3/FuzzyCountry.py
ingester3/Priogrid.py
ingester3/ViewsMonth.py
ingester3/__init__.py
ingester3/config.py
ingester3/extensions.py
ingester3/log.py
ingester3/scratch.py
ingester3/timestamp.cache
ingester3-2.1.1.dist-info/METADATA
ingester3-2.1.1.dist-info/WHEEL
ingester3-2.1.1.dist-info/RECORD
