Metadata-Version: 2.3
Name: ingester3
Version: 2.1.1
Summary: Data ingester for ViEWS3.
License: MIT
Author: Mihai Croicu
Author-email: mihai.croicu@pcr.uu.se
Requires-Python: >=3.9,<4.0
Classifier: License :: OSI Approved :: MIT License
Classifier: Programming Language :: Python :: 3
Classifier: Programming Language :: Python :: 3.9
Classifier: Programming Language :: Python :: 3.10
Classifier: Programming Language :: Python :: 3.11
Classifier: Programming Language :: Python :: 3.12
Classifier: Programming Language :: Python :: 3.13
Requires-Dist: cryptography (>36.0)
Requires-Dist: diskcache (>=5.0.0,<6.0.0)
Requires-Dist: levenshtein (>=0.20,<0.21)
Requires-Dist: numpy (>1.24)
Requires-Dist: pandas (>1.2.3)
Requires-Dist: psycopg2-binary (>=2.8,<3.0)
Requires-Dist: python-dotenv (>=0.18,<0.19)
Requires-Dist: sqlalchemy (>=1.3,<2.0)
Project-URL: Homepage, https://github.com/UppsalaConflictDataProgram/ingester3>
